{
  "oifm_id": "OIFM_GMTS_012551",
  "name": "defective pubic ossification",
  "description": "Abnormal development of the pubic bones seen on imaging, potentially due to congenital causes.",
  "tags": [
    "pediatric",
    "XR",
    "CT",
    "pelvis",
    "bone",
    "congenital anomaly",
    "diagnosis"
  ],
  "contributors": [
    {
      "name": "Radiology Gamuts Ontology",
      "code": "GMTS",
      "url": "https://gamuts.net/"
    }
  ],
  "attributes": [
    {
      "oifma_id": "OIFMA_GMTS_115438",
      "name": "presence",
      "description": "Presence or absence of defective pubic ossification",
      "type": "choice",
      "values": [
        {
          "value_code": "OIFMA_GMTS_115438.0",
          "name": "absent",
          "description": "Defective pubic ossification is absent",
          "index_codes": [
            {
              "system": "RADLEX",
              "code": "RID28473",
              "display": "absent"
            },
            {
              "system": "SNOMED",
              "code": "2667000",
              "display": "Absent (qualifier value)"
            }
          ]
        },
        {
          "value_code": "OIFMA_GMTS_115438.1",
          "name": "present",
          "description": "Defective pubic ossification is present",
          "index_codes": [
            {
              "system": "RADLEX",
              "code": "RID28472",
              "display": "present"
            },
            {
              "system": "SNOMED",
              "code": "52101004",
              "display": "Present (qualifier value)"
            }
          ]
        },
        {
          "value_code": "OIFMA_GMTS_115438.2",
          "name": "indeterminate",
          "description": "Presence of defective pubic ossification cannot be determined",
          "index_codes": [
            {
              "system": "RADLEX",
              "code": "RID39110",
              "display": "indeterminate"
            },
            {
              "system": "SNOMED",
              "code": "82334004",
              "display": "Indeterminate (qualifier value)"
            }
          ]
        },
        {
          "value_code": "OIFMA_GMTS_115438.3",
          "name": "unknown",
          "description": "Presence of defective pubic ossification is unknown",
          "index_codes": [
            {
              "system": "RADLEX",
              "code": "RID5655",
              "display": "unknown"
            },
            {
              "system": "SNOMED",
              "code": "261665006",
              "display": "Unknown (qualifier value)"
            }
          ]
        }
      ],
      "required": false,
      "max_selected": 1,
      "index_codes": [
        {
          "system": "SNOMED",
          "code": "705057003",
          "display": "Presence (property) (qualifier value)"
        }
      ]
    },
    {
      "oifma_id": "OIFMA_GMTS_980134",
      "name": "change from prior",
      "description": "Whether and how a defective pubic ossification has changed over time",
      "type": "choice",
      "values": [
        {
          "value_code": "OIFMA_GMTS_980134.0",
          "name": "unchanged",
          "description": "Defective pubic ossification is unchanged",
          "index_codes": [
            {
              "system": "RADLEX",
              "code": "RID39268",
              "display": "unchanged"
            },
            {
              "system": "SNOMED",
              "code": "260388006",
              "display": "No status change (qualifier value)"
            }
          ]
        },
        {
          "value_code": "OIFMA_GMTS_980134.1",
          "name": "stable",
          "description": "Defective pubic ossification is stable",
          "index_codes": [
            {
              "system": "RADLEX",
              "code": "RID5734",
              "display": "stable"
            },
            {
              "system": "SNOMED",
              "code": "58158008",
              "display": "Stable (qualifier value)"
            }
          ]
        },
        {
          "value_code": "OIFMA_GMTS_980134.2",
          "name": "new",
          "description": "Defective pubic ossification is new",
          "index_codes": [
            {
              "system": "RADLEX",
              "code": "RID5720",
              "display": "new"
            },
            {
              "system": "SNOMED",
              "code": "7147002",
              "display": "New (qualifier value)"
            }
          ]
        },
        {
          "value_code": "OIFMA_GMTS_980134.3",
          "name": "resolved",
          "description": "Defective pubic ossification seen on a prior exam has resolved"
        },
        {
          "value_code": "OIFMA_GMTS_980134.4",
          "name": "increased",
          "description": "Defective pubic ossification has increased",
          "index_codes": [
            {
              "system": "RADLEX",
              "code": "RID36043",
              "display": "increased"
            },
            {
              "system": "SNOMED",
              "code": "35105006",
              "display": "Increased (qualifier value)"
            }
          ]
        },
        {
          "value_code": "OIFMA_GMTS_980134.5",
          "name": "decreased",
          "description": "Defective pubic ossification has decreased",
          "index_codes": [
            {
              "system": "RADLEX",
              "code": "RID36044",
              "display": "decreased"
            },
            {
              "system": "SNOMED",
              "code": "1250004",
              "display": "Decreased (qualifier value)"
            }
          ]
        },
        {
          "value_code": "OIFMA_GMTS_980134.6",
          "name": "larger",
          "description": "Defective pubic ossification is larger",
          "index_codes": [
            {
              "system": "RADLEX",
              "code": "RID5791",
              "display": "enlarged"
            },
            {
              "system": "SNOMED",
              "code": "263768009",
              "display": "Greater (qualifier value)"
            }
          ]
        },
        {
          "value_code": "OIFMA_GMTS_980134.7",
          "name": "smaller",
          "description": "Defective pubic ossification is smaller",
          "index_codes": [
            {
              "system": "RADLEX",
              "code": "RID38669",
              "display": "diminished"
            },
            {
              "system": "SNOMED",
              "code": "263796003",
              "display": "Lesser (qualifier value)"
            }
          ]
        }
      ],
      "required": false,
      "max_selected": 1,
      "index_codes": [
        {
          "system": "RADLEX",
          "code": "RID49896",
          "display": "change"
        },
        {
          "system": "SNOMED",
          "code": "263703002",
          "display": "Changed status (qualifier value)"
        }
      ]
    }
  ],
  "index_codes": [
    {
      "system": "GAMUTS",
      "code": "12551",
      "display": "defective pubic ossification"
    }
  ]
}