{
  "oifm_id": "OIFM_OIDM_738859",
  "name": "meningioma",
  "description": "A typically benign, dural-based extra-axial neoplasm that on head CT appears as a well-circumscribed slightly hyperdense or isodense mass, often with calcification, homogeneous intense enhancement, and adjacent hyperostosis. It is the most common extra-axial intracranial tumor.",
  "tags": [
    "head",
    "CT",
    "finding"
  ],
  "contributors": [
    {
      "github_username": "hoodcm",
      "email": "chood@mgh.harvard.edu",
      "name": "C. Michael Hood, MD",
      "organization_code": "MGB"
    },
    {
      "name": "Open Imaging Data Model",
      "code": "OIDM"
    }
  ],
  "attributes": [
    {
      "oifma_id": "OIFMA_OIDM_451758",
      "name": "presence",
      "description": "Presence or absence of meningioma",
      "type": "choice",
      "values": [
        {
          "value_code": "OIFMA_OIDM_451758.0",
          "name": "absent",
          "description": "Meningioma is absent",
          "index_codes": [
            {
              "system": "RADLEX",
              "code": "RID28473",
              "display": "absent"
            },
            {
              "system": "SNOMED",
              "code": "2667000",
              "display": "Absent (qualifier value)"
            }
          ]
        },
        {
          "value_code": "OIFMA_OIDM_451758.1",
          "name": "present",
          "description": "Meningioma is present",
          "index_codes": [
            {
              "system": "RADLEX",
              "code": "RID28472",
              "display": "present"
            },
            {
              "system": "SNOMED",
              "code": "52101004",
              "display": "Present (qualifier value)"
            }
          ]
        },
        {
          "value_code": "OIFMA_OIDM_451758.2",
          "name": "indeterminate",
          "description": "Presence of meningioma cannot be determined",
          "index_codes": [
            {
              "system": "RADLEX",
              "code": "RID39110",
              "display": "indeterminate"
            },
            {
              "system": "SNOMED",
              "code": "82334004",
              "display": "Indeterminate (qualifier value)"
            }
          ]
        },
        {
          "value_code": "OIFMA_OIDM_451758.3",
          "name": "unknown",
          "description": "Presence of meningioma is unknown",
          "index_codes": [
            {
              "system": "RADLEX",
              "code": "RID5655",
              "display": "unknown"
            },
            {
              "system": "SNOMED",
              "code": "261665006",
              "display": "Unknown (qualifier value)"
            }
          ]
        }
      ],
      "required": false,
      "max_selected": 1,
      "index_codes": [
        {
          "system": "SNOMED",
          "code": "705057003",
          "display": "Presence (property) (qualifier value)"
        }
      ]
    },
    {
      "oifma_id": "OIFMA_OIDM_511195",
      "name": "change from prior",
      "description": "Whether and how meningioma has changed over time",
      "type": "choice",
      "values": [
        {
          "value_code": "OIFMA_OIDM_511195.0",
          "name": "unchanged",
          "description": "Meningioma is unchanged",
          "index_codes": [
            {
              "system": "RADLEX",
              "code": "RID39268",
              "display": "unchanged"
            },
            {
              "system": "SNOMED",
              "code": "260388006",
              "display": "No status change (qualifier value)"
            }
          ]
        },
        {
          "value_code": "OIFMA_OIDM_511195.1",
          "name": "stable",
          "description": "Meningioma is stable",
          "index_codes": [
            {
              "system": "RADLEX",
              "code": "RID5734",
              "display": "stable"
            },
            {
              "system": "SNOMED",
              "code": "58158008",
              "display": "Stable (qualifier value)"
            }
          ]
        },
        {
          "value_code": "OIFMA_OIDM_511195.2",
          "name": "new",
          "description": "Meningioma is new",
          "index_codes": [
            {
              "system": "RADLEX",
              "code": "RID5720",
              "display": "new"
            },
            {
              "system": "SNOMED",
              "code": "7147002",
              "display": "New (qualifier value)"
            }
          ]
        },
        {
          "value_code": "OIFMA_OIDM_511195.3",
          "name": "resolved",
          "description": "Meningioma seen on a prior exam has resolved"
        },
        {
          "value_code": "OIFMA_OIDM_511195.4",
          "name": "larger",
          "description": "Meningioma is larger",
          "index_codes": [
            {
              "system": "RADLEX",
              "code": "RID5791",
              "display": "enlarged"
            },
            {
              "system": "SNOMED",
              "code": "263768009",
              "display": "Greater (qualifier value)"
            }
          ]
        },
        {
          "value_code": "OIFMA_OIDM_511195.5",
          "name": "smaller",
          "description": "Meningioma is smaller",
          "index_codes": [
            {
              "system": "RADLEX",
              "code": "RID38669",
              "display": "diminished"
            },
            {
              "system": "SNOMED",
              "code": "263796003",
              "display": "Lesser (qualifier value)"
            }
          ]
        }
      ],
      "required": false,
      "max_selected": 1,
      "index_codes": [
        {
          "system": "RADLEX",
          "code": "RID49896",
          "display": "change"
        },
        {
          "system": "SNOMED",
          "code": "263703002",
          "display": "Changed status (qualifier value)"
        }
      ]
    }
  ]
}