{
  "oifm_id": "OIFM_CDE_000116",
  "name": "Aging Brain",
  "description": "Aging Brain",
  "attributes": [
    {
      "oifma_id": "OIFMA_CDE_000749",
      "name": "Global cortical atrophy scale",
      "description": "system to assess cerebral atrophy, especially in the context of neurodegenerative diseases",
      "type": "numeric",
      "minimum": 0,
      "maximum": 3,
      "unit": "unit",
      "required": false,
      "index_codes": null
    },
    {
      "oifma_id": "OIFMA_CDE_000750",
      "name": "Posterior parietal atrophy score",
      "description": "Koedman Score",
      "type": "numeric",
      "minimum": 0,
      "maximum": 3,
      "unit": "unit",
      "required": false,
      "index_codes": null
    },
    {
      "oifma_id": "OIFMA_CDE_000751",
      "name": "Total brain volume",
      "description": "",
      "type": "numeric",
      "minimum": 0,
      "maximum": 100,
      "unit": "mm3",
      "required": false,
      "index_codes": null
    },
    {
      "oifma_id": "OIFMA_CDE_000752",
      "name": "Ventricular system volume",
      "description": "",
      "type": "numeric",
      "minimum": 0,
      "maximum": 100,
      "unit": "mm3",
      "required": false,
      "index_codes": null
    },
    {
      "oifma_id": "OIFMA_CDE_000753",
      "name": "Hippocampi volume",
      "description": "",
      "type": "numeric",
      "minimum": 0,
      "maximum": 100,
      "unit": "mm3",
      "required": false,
      "index_codes": null
    },
    {
      "oifma_id": "OIFMA_CDE_000754",
      "name": "Frontal lobes volume",
      "description": "",
      "type": "numeric",
      "minimum": 0,
      "maximum": 100,
      "unit": "mm3",
      "required": false,
      "index_codes": null
    },
    {
      "oifma_id": "OIFMA_CDE_000755",
      "name": "Temporal lobes volume",
      "description": "",
      "type": "numeric",
      "minimum": 0,
      "maximum": 100,
      "unit": "mm3",
      "required": false,
      "index_codes": null
    },
    {
      "oifma_id": "OIFMA_CDE_000756",
      "name": "Fzekas scale ",
      "description": "Fzekas Scale (from FLAIR sequence)",
      "type": "numeric",
      "minimum": 0,
      "maximum": 6,
      "unit": "unit",
      "required": false,
      "index_codes": null
    }
  ],
  "index_codes": [
    {
      "system": "RADELEMENT",
      "code": "RDES116",
      "display": "aging brain"
    },
    {
      "system": "RADLEX",
      "code": "RID6434",
      "display": "brain"
    }
  ]
}