{
  "oifm_id": "OIFM_CDE_000227",
  "name": "Chest Radiograph Pulmonary Nodules",
  "description": "Chest Radiograph Pulmonary Nodules",
  "attributes": [
    {
      "oifma_id": "OIFMA_CDE_001465",
      "name": "Presence",
      "description": "nodules < 3 cm ",
      "type": "choice",
      "required": false,
      "values": [],
      "index_codes": []
    }
  ],
  "index_codes": [
    {
      "system": "RADELEMENT",
      "code": "RDES227",
      "display": "chest radiograph pulmonary nodules"
    }
  ],
  "body_parts": []
}