{
    "model_definitions": [
        {
            "oifm_id": "OIFM_MSFT_134126",
            "name": "abdominal aortic aneurysm",
            "file_path": ".\\defs\\abdominal_aortic_aneurysm.fm.json"
        },
        {
            "oifm_id": "OIFM_MSFT_573630",
            "name": "aortic dissection",
            "file_path": ".\\defs\\aortic_dissection.fm.json"
        },
        {
            "oifm_id": "OIFM_MSFT_356221",
            "name": "Breast density",
            "file_path": ".\\defs\\breast_density.fm.json"
        },
        {
            "oifm_id": "OIFM_MSFT_156954",
            "name": "Mammographic malignancy assessment",
            "file_path": ".\\defs\\breast_malignancy_risk.fm.json"
        },
        {
            "oifm_id": "OIFM_MSFT_932618",
            "name": "pulmonary embolism",
            "file_path": ".\\defs\\pulmonary_embolism.fm.json"
        },
        {
            "oifm_id": "OIFM_MSFT_367670",
            "name": "Ventricular diameters",
            "file_path": ".\\defs\\ventricular_diameters.fm.json"
        }
    ]
}